Workbook

Sheet 配置总览
B2: 资产配置与再平衡计算器
B4: 资产 | C4: 角色 | D4: 目标权重 | E4: 当前市值(输入) | F4: 当前权重 | G4: 偏离(pp) | H4: 调仓金额 | I4: 触发再平衡
B5: 现金/货基 | C5: 现金 | D5: 0.17 | F5: =IF(E5="","",E5/$E$17) | G5: =IF(F5="","",(F5-D5)*100) | H5: =IF(F5="","",D5*$E$17-E5) | I5: =IF(F5="","",IF(ABS(G5)>=5,"触发","—"))
B6: 国债/纯债 | C6: 核心 | D6: 0.15 | F6: =IF(E6="","",E6/$E$17) | G6: =IF(F6="","",(F6-D6)*100) | H6: =IF(F6="","",D6*$E$17-E6) | I6: =IF(F6="","",IF(ABS(G6)>=5,"触发","—"))
B7: 沪深300 | C7: 核心 | D7: 0.12 | F7: =IF(E7="","",E7/$E$17) | G7: =IF(F7="","",(F7-D7)*100) | H7: =IF(F7="","",D7*$E$17-E7) | I7: =IF(F7="","",IF(ABS(G7)>=5,"触发","—"))
B8: 标普500 | C8: 核心 | D8: 0.12 | F8: =IF(E8="","",E8/$E$17) | G8: =IF(F8="","",(F8-D8)*100) | H8: =IF(F8="","",D8*$E$17-E8) | I8: =IF(F8="","",IF(ABS(G8)>=5,"触发","—"))
B9: 中证500 | C9: 核心 | D9: 0.08 | F9: =IF(E9="","",E9/$E$17) | G9: =IF(F9="","",(F9-D9)*100) | H9: =IF(F9="","",D9*$E$17-E9) | I9: =IF(F9="","",IF(ABS(G9)>=5,"触发","—"))
B10: 纳指100 | C10: 核心 | D10: 0.08 | F10: =IF(E10="","",E10/$E$17) | G10: =IF(F10="","",(F10-D10)*100) | H10: =IF(F10="","",D10*$E$17-E10) | I10: =IF(F10="","",IF(ABS(G10)>=5,"触发","—"))
B11: 黄金 | C11: 核心 | D11: 0.08 | F11: =IF(E11="","",E11/$E$17) | G11: =IF(F11="","",(F11-D11)*100) | H11: =IF(F11="","",D11*$E$17-E11) | I11: =IF(F11="","",IF(ABS(G11)>=5,"触发","—"))
B12: 创业板指 | C12: 核心 | D12: 0.05 | F12: =IF(E12="","",E12/$E$17) | G12: =IF(F12="","",(F12-D12)*100) | H12: =IF(F12="","",D12*$E$17-E12) | I12: =IF(F12="","",IF(ABS(G12)>=5,"触发","—"))
B13: 中证红利 | C13: 防守 | D13: 0.05 | F13: =IF(E13="","",E13/$E$17) | G13: =IF(F13="","",(F13-D13)*100) | H13: =IF(F13="","",D13*$E$17-E13) | I13: =IF(F13="","",IF(ABS(G13)>=5,"触发","—"))
B14: 全指信息 | C14: 行业卫星 | D14: 0.04 | F14: =IF(E14="","",E14/$E$17) | G14: =IF(F14="","",(F14-D14)*100) | H14: =IF(F14="","",D14*$E$17-E14) | I14: =IF(F14="","",IF(ABS(G14)>=5,"触发","—"))
B15: 新能源车 | C15: 行业卫星 | D15: 0.04 | F15: =IF(E15="","",E15/$E$17) | G15: =IF(F15="","",(F15-D15)*100) | H15: =IF(F15="","",D15*$E$17-E15) | I15: =IF(F15="","",IF(ABS(G15)>=5,"触发","—"))
B16: 全指医药 | C16: 行业卫星 | D16: 0.02 | F16: =IF(E16="","",E16/$E$17) | G16: =IF(F16="","",(F16-D16)*100) | H16: =IF(F16="","",D16*$E$17-E16) | I16: =IF(F16="","",IF(ABS(G16)>=5,"触发","—"))
B17: 合计 | D17: =SUM(D5:D16) -> 1 | E17: =SUM(E5:E16) -> 0
B19: 使用：每月/每季把各资产最新市值填入蓝色列 → 当前权重、偏离与调仓金额自动计算；偏离≥±5pp 即触发再平衡。
B20: 调仓优先用新定投资金『只买不卖』实现；卖出优先卖超配的卫星仓。

Sheet 定投计划
B2: 估值加权定投计划
B3: 每月定投总额(输入) | C3: 10000
B4: 资产 | C4: 目标权重 | D4: 基准月投额 | E4: 估值分位(输入) | F4: 定投倍数 | G4: 实际定投额
B5: 现金/货基 | C5: =配置总览!D5 -> 0.17 | D5: =C5*$C$3 -> 1700 | F5: =IF(E5="",1,IF(E5<0.2,2,IF(E5<0.4,1.5,IF(E5<0.6,1,IF(E5<0.8,0.5,0))))) -> 1 | G5: =D5*F5 -> 1700
B6: 国债/纯债 | C6: =配置总览!D6 -> 0.15 | D6: =C6*$C$3 -> 1500 | F6: =IF(E6="",1,IF(E6<0.2,2,IF(E6<0.4,1.5,IF(E6<0.6,1,IF(E6<0.8,0.5,0))))) -> 1 | G6: =D6*F6 -> 1500
B7: 沪深300 | C7: =配置总览!D7 -> 0.12 | D7: =C7*$C$3 -> 1200 | E7: 0.48497324 | F7: =IF(E7="",1,IF(E7<0.2,2,IF(E7<0.4,1.5,IF(E7<0.6,1,IF(E7<0.8,0.5,0))))) -> 1 | G7: =D7*F7 -> 1200
B8: 标普500 | C8: =配置总览!D8 -> 0.12 | D8: =C8*$C$3 -> 1200 | E8: 1 | F8: =IF(E8="",1,IF(E8<0.2,2,IF(E8<0.4,1.5,IF(E8<0.6,1,IF(E8<0.8,0.5,0))))) -> 0 | G8: =D8*F8 -> 0
B9: 中证500 | C9: =配置总览!D9 -> 0.08 | D9: =C9*$C$3 -> 800 | E9: 0.70864198 | F9: =IF(E9="",1,IF(E9<0.2,2,IF(E9<0.4,1.5,IF(E9<0.6,1,IF(E9<0.8,0.5,0))))) -> 0.5 | G9: =D9*F9 -> 400
B10: 纳指100 | C10: =配置总览!D10 -> 0.08 | D10: =C10*$C$3 -> 800 | E10: 1 | F10: =IF(E10="",1,IF(E10<0.2,2,IF(E10<0.4,1.5,IF(E10<0.6,1,IF(E10<0.8,0.5,0))))) -> 0 | G10: =D10*F10 -> 0
B11: 黄金 | C11: =配置总览!D11 -> 0.08 | D11: =C11*$C$3 -> 800 | F11: =IF(E11="",1,IF(E11<0.2,2,IF(E11<0.4,1.5,IF(E11<0.6,1,IF(E11<0.8,0.5,0))))) -> 1 | G11: =D11*F11 -> 800
B12: 创业板指 | C12: =配置总览!D12 -> 0.05 | D12: =C12*$C$3 -> 500 | E12: 0.83889576 | F12: =IF(E12="",1,IF(E12<0.2,2,IF(E12<0.4,1.5,IF(E12<0.6,1,IF(E12<0.8,0.5,0))))) -> 0 | G12: =D12*F12 -> 0
B13: 中证红利 | C13: =配置总览!D13 -> 0.05 | D13: =C13*$C$3 -> 500 | E13: 0.7473251 | F13: =IF(E13="",1,IF(E13<0.2,2,IF(E13<0.4,1.5,IF(E13<0.6,1,IF(E13<0.8,0.5,0))))) -> 0.5 | G13: =D13*F13 -> 250
B14: 全指信息 | C14: =配置总览!D14 -> 0.04 | D14: =C14*$C$3 -> 400 | E14: 0.61111111 | F14: =IF(E14="",1,IF(E14<0.2,2,IF(E14<0.4,1.5,IF(E14<0.6,1,IF(E14<0.8,0.5,0))))) -> 0.5 | G14: =D14*F14 -> 200
B15: 新能源车 | C15: =配置总览!D15 -> 0.04 | D15: =C15*$C$3 -> 400 | E15: 0.25833704 | F15: =IF(E15="",1,IF(E15<0.2,2,IF(E15<0.4,1.5,IF(E15<0.6,1,IF(E15<0.8,0.5,0))))) -> 1.5 | G15: =D15*F15 -> 600
B16: 全指医药 | C16: =配置总览!D16 -> 0.02 | D16: =C16*$C$3 -> 200 | E16: 0.14156379 | F16: =IF(E16="",1,IF(E16<0.2,2,IF(E16<0.4,1.5,IF(E16<0.6,1,IF(E16<0.8,0.5,0))))) -> 2 | G16: =D16*F16 -> 400
B17: 合计 | D17: =SUM(D5:D16) -> 10000 | G17: =SUM(G5:G16) -> 7050
B19: 定投倍数规则（股票资产）：<20%→2x｜20-40%→1.5x｜40-60%→1x｜60-80%→0.5x｜≥80%→停投(0x)；债券/黄金/现金固定 1x。
B20: 估值分位每月初从网站『估值温度』页复制更新（蓝色列），倍数与金额自动重算。

Sheet 估值跟踪
B2: 估值分位跟踪（近10年滚动）
B4: 资产 | C4: 指数代码 | D4: 估值口径 | E4: 当前PE | F4: 历史分位 | G4: 估值区 | H4: 数据截至 | I4: 备注
B5: 沪深300 | C5: 000300.SH | D5: PE-TTM | F5: 0.48497324 | G5: =IF(F5="","",IF(F5<0.2,"低估",IF(F5<0.4,"合理偏低",IF(F5<0.6,"合理",IF(F5<0.8,"合理偏高","高估"))))) -> 合理 | H5: 2026-09-30
B6: 中证500 | C6: 000905.SH | D6: PE-TTM | F6: 0.70864198 | G6: =IF(F6="","",IF(F6<0.2,"低估",IF(F6<0.4,"合理偏低",IF(F6<0.6,"合理",IF(F6<0.8,"合理偏高","高估"))))) -> 合理偏高 | H6: 2026-09-30
B7: 创业板指 | C7: 399006.SZ | D7: PE-TTM | F7: 0.83889576 | G7: =IF(F7="","",IF(F7<0.2,"低估",IF(F7<0.4,"合理偏低",IF(F7<0.6,"合理",IF(F7<0.8,"合理偏高","高估"))))) -> 高估 | H7: 2026-09-30 | I7: PE/PB缺失，用价格分位替代
B8: 中证红利 | C8: 000922.CSI | D8: PE-TTM | F8: 0.7473251 | G8: =IF(F8="","",IF(F8<0.2,"低估",IF(F8<0.4,"合理偏低",IF(F8<0.6,"合理",IF(F8<0.8,"合理偏高","高估"))))) -> 合理偏高 | H8: 2026-09-30
B9: 标普500 | C9: SPX | D9: 席勒PE | F9: 1 | G9: =IF(F9="","",IF(F9<0.2,"低估",IF(F9<0.4,"合理偏低",IF(F9<0.6,"合理",IF(F9<0.8,"合理偏高","高估"))))) -> 高估 | H9: 2026-10-02
B10: 纳指100 | C10: NDX | D10: 价格分位 | F10: 1 | G10: =IF(F10="","",IF(F10<0.2,"低估",IF(F10<0.4,"合理偏低",IF(F10<0.6,"合理",IF(F10<0.8,"合理偏高","高估"))))) -> 高估 | H10: 2026-10-02 | I10: 价格分位替代PE（弱均值回归假设）
B11: 中证白酒 | C11: 399997.SZ | D11: PE-TTM | F11: 0.13415638 | G11: =IF(F11="","",IF(F11<0.2,"低估",IF(F11<0.4,"合理偏低",IF(F11<0.6,"合理",IF(F11<0.8,"合理偏高","高估"))))) -> 低估 | H11: 2026-09-30
B12: 全指医药 | C12: 000991.CSI | D12: PE-TTM | F12: 0.14156379 | G12: =IF(F12="","",IF(F12<0.2,"低估",IF(F12<0.4,"合理偏低",IF(F12<0.6,"合理",IF(F12<0.8,"合理偏高","高估"))))) -> 低估 | H12: 2026-09-30
B13: 全指信息 | C13: 000993.CSI | D13: PE-TTM | F13: 0.61111111 | G13: =IF(F13="","",IF(F13<0.2,"低估",IF(F13<0.4,"合理偏低",IF(F13<0.6,"合理",IF(F13<0.8,"合理偏高","高估"))))) -> 合理偏高 | H13: 2026-09-30
B14: 中证消费 | C14: 000932.CSI | D14: PE-TTM | F14: 0.10946502 | G14: =IF(F14="","",IF(F14<0.2,"低估",IF(F14<0.4,"合理偏低",IF(F14<0.6,"合理",IF(F14<0.8,"合理偏高","高估"))))) -> 低估 | H14: 2026-09-30
B15: 中证军工 | C15: 399967.SZ | D15: PE-TTM | F15: 0.28559671 | G15: =IF(F15="","",IF(F15<0.2,"低估",IF(F15<0.4,"合理偏低",IF(F15<0.6,"合理",IF(F15<0.8,"合理偏高","高估"))))) -> 合理偏低 | H15: 2026-09-30
B16: 证券公司 | C16: 399975.SZ | D16: PE-TTM | F16: 0.0012345679 | G16: =IF(F16="","",IF(F16<0.2,"低估",IF(F16<0.4,"合理偏低",IF(F16<0.6,"合理",IF(F16<0.8,"合理偏高","高估"))))) -> 低估 | H16: 2026-09-30
B17: 新能源车 | C17: 930997.CSI | D17: PE-TTM | F17: 0.25833704 | G17: =IF(F17="","",IF(F17<0.2,"低估",IF(F17<0.4,"合理偏低",IF(F17<0.6,"合理",IF(F17<0.8,"合理偏高","高估"))))) -> 合理偏低 | H17: 2026-09-30
B18: 恒生科技 | C18: HSTECH | D18: 价格分位 | F18: 0.2934927 | G18: =IF(F18="","",IF(F18<0.2,"低估",IF(F18<0.4,"合理偏低",IF(F18<0.6,"合理",IF(F18<0.8,"合理偏高","高估"))))) -> 合理偏低 | H18: 2026-10-02 | I18: 价格分位替代PE（弱均值回归假设）
B19: 日经225 | C19: N225 | D19: 价格分位 | G19: =IF(F19="","",IF(F19<0.2,"低估",IF(F19<0.4,"合理偏低",IF(F19<0.6,"合理",IF(F19<0.8,"合理偏高","高估"))))) | I19: 价格序列缺失
B22: 绿色=便宜(低分位)，红色=贵(高分位)。当前值预填自引擎最新输出，PE 列可从网站『估值温度』页核对更新。

Sheet 信号面板
B2: 四维打分卡（0-100，估值40/趋势30/资金15/宏观15）
B4: 资产 | C4: 估值分 | D4: 趋势分 | E4: 资金分 | F4: 宏观分 | G4: 总分 | H4: 建议
B5: 沪深300 | C5: 51.5 | D5: 62 | E5: 33 | F5: 50 | G5: =IF(COUNT(C5:F5)=0,"—",ROUND((IF(ISNUMBER(C5),C5*40,0)+IF(ISNUMBER(D5),D5*30,0)+IF(ISNUMBER(E5),E5*15,0)+IF(ISNUMBER(F5),F5*15,0))/(IF(ISNUMBER(C5),40,0)+IF(ISNUMBER(D5),30,0)+IF(ISNUMBER(E5),15,0)+IF(ISNUMBER(F5),15,0)),1)) -> 51.7 | H5: =IF(G5="—","待补数据",IF(G5>=65,"偏多：按倍数定投/持有",IF(G5<=40,"偏空：控制仓位","中性：按计划定投"))) -> 中性：按计划定投
B6: 中证500 | C6: 29.1 | D6: 67.9 | E6: 32.9 | F6: 50 | G6: =IF(COUNT(C6:F6)=0,"—",ROUND((IF(ISNUMBER(C6),C6*40,0)+IF(ISNUMBER(D6),D6*30,0)+IF(ISNUMBER(E6),E6*15,0)+IF(ISNUMBER(F6),F6*15,0))/(IF(ISNUMBER(C6),40,0)+IF(ISNUMBER(D6),30,0)+IF(ISNUMBER(E6),15,0)+IF(ISNUMBER(F6),15,0)),1)) -> 44.4 | H6: =IF(G6="—","待补数据",IF(G6>=65,"偏多：按倍数定投/持有",IF(G6<=40,"偏空：控制仓位","中性：按计划定投"))) -> 中性：按计划定投
B7: 创业板指 | C7: 16.1 | D7: 72.1 | E7: 36.7 | F7: 50 | G7: =IF(COUNT(C7:F7)=0,"—",ROUND((IF(ISNUMBER(C7),C7*40,0)+IF(ISNUMBER(D7),D7*30,0)+IF(ISNUMBER(E7),E7*15,0)+IF(ISNUMBER(F7),F7*15,0))/(IF(ISNUMBER(C7),40,0)+IF(ISNUMBER(D7),30,0)+IF(ISNUMBER(E7),15,0)+IF(ISNUMBER(F7),15,0)),1)) -> 41.1 | H7: =IF(G7="—","待补数据",IF(G7>=65,"偏多：按倍数定投/持有",IF(G7<=40,"偏空：控制仓位","中性：按计划定投"))) -> 中性：按计划定投
B8: 中证红利 | C8: 25.3 | D8: 57.5 | E8: 39.5 | F8: 50 | G8: =IF(COUNT(C8:F8)=0,"—",ROUND((IF(ISNUMBER(C8),C8*40,0)+IF(ISNUMBER(D8),D8*30,0)+IF(ISNUMBER(E8),E8*15,0)+IF(ISNUMBER(F8),F8*15,0))/(IF(ISNUMBER(C8),40,0)+IF(ISNUMBER(D8),30,0)+IF(ISNUMBER(E8),15,0)+IF(ISNUMBER(F8),15,0)),1)) -> 40.8 | H8: =IF(G8="—","待补数据",IF(G8>=65,"偏多：按倍数定投/持有",IF(G8<=40,"偏空：控制仓位","中性：按计划定投"))) -> 中性：按计划定投
B9: 标普500 | C9: 0 | D9: 92.8 | E9: 21.1 | F9: 50 | G9: =IF(COUNT(C9:F9)=0,"—",ROUND((IF(ISNUMBER(C9),C9*40,0)+IF(ISNUMBER(D9),D9*30,0)+IF(ISNUMBER(E9),E9*15,0)+IF(ISNUMBER(F9),F9*15,0))/(IF(ISNUMBER(C9),40,0)+IF(ISNUMBER(D9),30,0)+IF(ISNUMBER(E9),15,0)+IF(ISNUMBER(F9),15,0)),1)) -> 38.5 | H9: =IF(G9="—","待补数据",IF(G9>=65,"偏多：按倍数定投/持有",IF(G9<=40,"偏空：控制仓位","中性：按计划定投"))) -> 偏空：控制仓位
B10: 纳指100 | C10: 0 | D10: 95 | E10: 21.1 | F10: 50 | G10: =IF(COUNT(C10:F10)=0,"—",ROUND((IF(ISNUMBER(C10),C10*40,0)+IF(ISNUMBER(D10),D10*30,0)+IF(ISNUMBER(E10),E10*15,0)+IF(ISNUMBER(F10),F10*15,0))/(IF(ISNUMBER(C10),40,0)+IF(ISNUMBER(D10),30,0)+IF(ISNUMBER(E10),15,0)+IF(ISNUMBER(F10),15,0)),1)) -> 39.2 | H10: =IF(G10="—","待补数据",IF(G10>=65,"偏多：按倍数定投/持有",IF(G10<=40,"偏空：控制仓位","中性：按计划定投"))) -> 偏空：控制仓位
B11: 国债/纯债 | D11: 81.7 | E11: 73.1 | F11: 50 | G11: =IF(COUNT(C11:F11)=0,"—",ROUND((IF(ISNUMBER(C11),C11*40,0)+IF(ISNUMBER(D11),D11*30,0)+IF(ISNUMBER(E11),E11*15,0)+IF(ISNUMBER(F11),F11*15,0))/(IF(ISNUMBER(C11),40,0)+IF(ISNUMBER(D11),30,0)+IF(ISNUMBER(E11),15,0)+IF(ISNUMBER(F11),15,0)),1)) -> 71.6 | H11: =IF(G11="—","待补数据",IF(G11>=65,"偏多：按倍数定投/持有",IF(G11<=40,"偏空：控制仓位","中性：按计划定投"))) -> 偏多：按倍数定投/持有
B12: 黄金 | D12: 69.6 | E12: 57.4 | F12: 50 | G12: =IF(COUNT(C12:F12)=0,"—",ROUND((IF(ISNUMBER(C12),C12*40,0)+IF(ISNUMBER(D12),D12*30,0)+IF(ISNUMBER(E12),E12*15,0)+IF(ISNUMBER(F12),F12*15,0))/(IF(ISNUMBER(C12),40,0)+IF(ISNUMBER(D12),30,0)+IF(ISNUMBER(E12),15,0)+IF(ISNUMBER(F12),15,0)),1)) -> 61.7 | H12: =IF(G12="—","待补数据",IF(G12>=65,"偏多：按倍数定投/持有",IF(G12<=40,"偏空：控制仓位","中性：按计划定投"))) -> 中性：按计划定投
B13: 中证白酒 | C13: 86.6 | D13: 37.6 | E13: 32.8 | F13: 50 | G13: =IF(COUNT(C13:F13)=0,"—",ROUND((IF(ISNUMBER(C13),C13*40,0)+IF(ISNUMBER(D13),D13*30,0)+IF(ISNUMBER(E13),E13*15,0)+IF(ISNUMBER(F13),F13*15,0))/(IF(ISNUMBER(C13),40,0)+IF(ISNUMBER(D13),30,0)+IF(ISNUMBER(E13),15,0)+IF(ISNUMBER(F13),15,0)),1)) -> 58.3 | H13: =IF(G13="—","待补数据",IF(G13>=65,"偏多：按倍数定投/持有",IF(G13<=40,"偏空：控制仓位","中性：按计划定投"))) -> 中性：按计划定投
B14: 全指医药 | C14: 85.8 | D14: 70.7 | E14: 34.7 | F14: 50 | G14: =IF(COUNT(C14:F14)=0,"—",ROUND((IF(ISNUMBER(C14),C14*40,0)+IF(ISNUMBER(D14),D14*30,0)+IF(ISNUMBER(E14),E14*15,0)+IF(ISNUMBER(F14),F14*15,0))/(IF(ISNUMBER(C14),40,0)+IF(ISNUMBER(D14),30,0)+IF(ISNUMBER(E14),15,0)+IF(ISNUMBER(F14),15,0)),1)) -> 68.2 | H14: =IF(G14="—","待补数据",IF(G14>=65,"偏多：按倍数定投/持有",IF(G14<=40,"偏空：控制仓位","中性：按计划定投"))) -> 偏多：按倍数定投/持有
B15: 全指信息 | C15: 38.9 | D15: 74.2 | E15: 31.9 | F15: 50 | G15: =IF(COUNT(C15:F15)=0,"—",ROUND((IF(ISNUMBER(C15),C15*40,0)+IF(ISNUMBER(D15),D15*30,0)+IF(ISNUMBER(E15),E15*15,0)+IF(ISNUMBER(F15),F15*15,0))/(IF(ISNUMBER(C15),40,0)+IF(ISNUMBER(D15),30,0)+IF(ISNUMBER(E15),15,0)+IF(ISNUMBER(F15),15,0)),1)) -> 50.1 | H15: =IF(G15="—","待补数据",IF(G15>=65,"偏多：按倍数定投/持有",IF(G15<=40,"偏空：控制仓位","中性：按计划定投"))) -> 中性：按计划定投
B16: 中证消费 | C16: 89.1 | D16: 40.8 | E16: 36.6 | F16: 50 | G16: =IF(COUNT(C16:F16)=0,"—",ROUND((IF(ISNUMBER(C16),C16*40,0)+IF(ISNUMBER(D16),D16*30,0)+IF(ISNUMBER(E16),E16*15,0)+IF(ISNUMBER(F16),F16*15,0))/(IF(ISNUMBER(C16),40,0)+IF(ISNUMBER(D16),30,0)+IF(ISNUMBER(E16),15,0)+IF(ISNUMBER(F16),15,0)),1)) -> 60.9 | H16: =IF(G16="—","待补数据",IF(G16>=65,"偏多：按倍数定投/持有",IF(G16<=40,"偏空：控制仓位","中性：按计划定投"))) -> 中性：按计划定投
B17: 中证军工 | C17: 71.4 | D17: 46.9 | E17: 34 | F17: 50 | G17: =IF(COUNT(C17:F17)=0,"—",ROUND((IF(ISNUMBER(C17),C17*40,0)+IF(ISNUMBER(D17),D17*30,0)+IF(ISNUMBER(E17),E17*15,0)+IF(ISNUMBER(F17),F17*15,0))/(IF(ISNUMBER(C17),40,0)+IF(ISNUMBER(D17),30,0)+IF(ISNUMBER(E17),15,0)+IF(ISNUMBER(F17),15,0)),1)) -> 55.2 | H17: =IF(G17="—","待补数据",IF(G17>=65,"偏多：按倍数定投/持有",IF(G17<=40,"偏空：控制仓位","中性：按计划定投"))) -> 中性：按计划定投
B18: 证券公司 | C18: 99.9 | D18: 43.1 | E18: 32.7 | F18: 50 | G18: =IF(COUNT(C18:F18)=0,"—",ROUND((IF(ISNUMBER(C18),C18*40,0)+IF(ISNUMBER(D18),D18*30,0)+IF(ISNUMBER(E18),E18*15,0)+IF(ISNUMBER(F18),F18*15,0))/(IF(ISNUMBER(C18),40,0)+IF(ISNUMBER(D18),30,0)+IF(ISNUMBER(E18),15,0)+IF(ISNUMBER(F18),15,0)),1)) -> 65.3 | H18: =IF(G18="—","待补数据",IF(G18>=65,"偏多：按倍数定投/持有",IF(G18<=40,"偏空：控制仓位","中性：按计划定投"))) -> 偏多：按倍数定投/持有
B19: 新能源车 | C19: 74.2 | D19: 65 | E19: 31.4 | F19: 50 | G19: =IF(COUNT(C19:F19)=0,"—",ROUND((IF(ISNUMBER(C19),C19*40,0)+IF(ISNUMBER(D19),D19*30,0)+IF(ISNUMBER(E19),E19*15,0)+IF(ISNUMBER(F19),F19*15,0))/(IF(ISNUMBER(C19),40,0)+IF(ISNUMBER(D19),30,0)+IF(ISNUMBER(E19),15,0)+IF(ISNUMBER(F19),15,0)),1)) -> 61.4 | H19: =IF(G19="—","待补数据",IF(G19>=65,"偏多：按倍数定投/持有",IF(G19<=40,"偏空：控制仓位","中性：按计划定投"))) -> 中性：按计划定投
B20: 恒生科技 | C20: 70.7 | D20: 40.7 | E20: 21.1 | F20: 50 | G20: =IF(COUNT(C20:F20)=0,"—",ROUND((IF(ISNUMBER(C20),C20*40,0)+IF(ISNUMBER(D20),D20*30,0)+IF(ISNUMBER(E20),E20*15,0)+IF(ISNUMBER(F20),F20*15,0))/(IF(ISNUMBER(C20),40,0)+IF(ISNUMBER(D20),30,0)+IF(ISNUMBER(E20),15,0)+IF(ISNUMBER(F20),15,0)),1)) -> 51.2 | H20: =IF(G20="—","待补数据",IF(G20>=65,"偏多：按倍数定投/持有",IF(G20<=40,"偏空：控制仓位","中性：按计划定投"))) -> 中性：按计划定投
B21: 日经225 | G21: =IF(COUNT(C21:F21)=0,"—",ROUND((IF(ISNUMBER(C21),C21*40,0)+IF(ISNUMBER(D21),D21*30,0)+IF(ISNUMBER(E21),E21*15,0)+IF(ISNUMBER(F21),F21*15,0))/(IF(ISNUMBER(C21),40,0)+IF(ISNUMBER(D21),30,0)+IF(ISNUMBER(E21),15,0)+IF(ISNUMBER(F21),15,0)),1)) -> — | H21: =IF(G21="—","待补数据",IF(G21>=65,"偏多：按倍数定投/持有",IF(G21<=40,"偏空：控制仓位","中性：按计划定投"))) -> 待补数据
B24: 各维度分预填自引擎最新输出（每次刷新后可从网站复制更新）；总分为活公式，缺项自动归一。

Sheet 持仓记录
B2: 买卖流水
B4: 日期 | C4: 代码 | D4: 名称 | E4: 方向 | F4: 份额 | G4: 单价 | H4: 金额 | I4: 费率 | J4: 费用 | K4: 备注
B5: 2026-10-04 | C5: 510300 | D5: 沪深300ETF | E5: 买入 | F5: 10000 | G5: 4.1 | H5: =F5*G5 -> 41000 | I5: 0.0003 | J5: =H5*I5 -> 12.3
B6: 2026-10-04 | C6: 110020 | D6: 易方达沪深300联接A | E6: 买入 | F6: 30000 | G6: 1.42 | H6: =F6*G6 -> 42600 | I6: 0.0012 | J6: =H6*I6 -> 51.12
H7: =IF(OR(F7="",G7=""),"",F7*G7) | J7: =IF(OR(H7="",I7=""),"",H7*I7)
H8: =IF(OR(F8="",G8=""),"",F8*G8) | J8: =IF(OR(H8="",I8=""),"",H8*I8)
H9: =IF(OR(F9="",G9=""),"",F9*G9) | J9: =IF(OR(H9="",I9=""),"",H9*I9)
H10: =IF(OR(F10="",G10=""),"",F10*G10) | J10: =IF(OR(H10="",I10=""),"",H10*I10)
H11: =IF(OR(F11="",G11=""),"",F11*G11) | J11: =IF(OR(H11="",I11=""),"",H11*I11)
H12: =IF(OR(F12="",G12=""),"",F12*G12) | J12: =IF(OR(H12="",I12=""),"",H12*I12)
H13: =IF(OR(F13="",G13=""),"",F13*G13) | J13: =IF(OR(H13="",I13=""),"",H13*I13)
H14: =IF(OR(F14="",G14=""),"",F14*G14) | J14: =IF(OR(H14="",I14=""),"",H14*I14)
H15: =IF(OR(F15="",G15=""),"",F15*G15) | J15: =IF(OR(H15="",I15=""),"",H15*I15)
H16: =IF(OR(F16="",G16=""),"",F16*G16) | J16: =IF(OR(H16="",I16=""),"",H16*I16)
H17: =IF(OR(F17="",G17=""),"",F17*G17) | J17: =IF(OR(H17="",I17=""),"",H17*I17)
H18: =IF(OR(F18="",G18=""),"",F18*G18) | J18: =IF(OR(H18="",I18=""),"",H18*I18)
... H26: =IF(OR(F26="",G26=""),"",F26*G26) | J26: =IF(OR(H26="",I26=""),"",H26*I26)
B27: 累计买入 | H27: =SUMIF(E5:E26,"买入",H5:H26) -> 83600
B28: 累计卖出 | H28: =SUMIF(E5:E26,"卖出",H5:H26) -> 0
B30: 方向列填『买入/卖出』；份额、单价、费率为蓝色输入列，金额与费用自动计算。

Sheet 月度清单
B2: 执行清单
B4: 频率 | C4: 事项 | D4: 对应工具 | E4: 完成(√)
B5: 每日 | C5: 看网站总览页有无红色预警（溢价/陈旧数据/回撤提醒），不交易 | D5: 网站-总览
B6: 每月 | C6: 按当月估值分位更新定投倍数，执行定投 | D6: 定投计划 / 网站-当前策略
B7: 每月 | C7: 检查行业卫星动量排名变化 | D7: 网站-趋势与动量
B8: 每月 | C8: 录入本月买卖流水 | D8: 持仓记录
B9: 每季 | C9: 更新各资产市值，跑再平衡计算器，偏离≥±5pp 执行调仓 | D9: 配置总览
B10: 每季 | C10: 核对 QDII 溢价，超 3% 的品种暂停买入 | D10: 网站-资金面
B11: 每年 | C11: 复核基金费率/规模/跟踪误差，必要时换同类替代 | D11: 基金筛选标准
B12: 每年 | C12: 复盘：每笔交易是否对应手册规则，写 3 条改进 | D12: 策略手册

Sheet Review
B2: 交叉校验
B4: 检查项 | C4: 期望 | D4: 实际 | E4: 状态
B5: 目标权重合计 = 100% | C5: 1 | D5: =SUM(配置总览!D5:D16) -> 1 | E5: =IF(ABS(C5-D5)<0.01,"✓ PASS","✗ FAIL") -> ✓ PASS
B6: 定投基准合计 = 月投总额 | C6: =定投计划!C3 -> 10000 | D6: =SUM(定投计划!D5:D16) -> 10000 | E6: =IF(ABS(C6-D6)<0.01,"✓ PASS","✗ FAIL") -> ✓ PASS
B7: 流水样本金额 = 份额×单价 | C7: =SUMPRODUCT(持仓记录!F5:F6,持仓记录!G5:G6) -> 83600 | D7: =SUM(持仓记录!H5:H6) -> 83600 | E7: =IF(ABS(C7-D7)<0.01,"✓ PASS","✗ FAIL") -> ✓ PASS
